ffxiahbot/__init__.py
ffxiahbot/__main__.py
ffxiahbot/common.py
ffxiahbot/config.py
ffxiahbot/database.py
ffxiahbot/item.py
ffxiahbot/itemlist.py
ffxiahbot/logutils.py
ffxiahbot/timeutils.py
ffxiahbot/apps/__init__.py
ffxiahbot/apps/broker.py
ffxiahbot/apps/clear.py
ffxiahbot/apps/refill.py
ffxiahbot/apps/scrub.py
ffxiahbot/auction/__init__.py
ffxiahbot/auction/browser.py
ffxiahbot/auction/buyer.py
ffxiahbot/auction/cleaner.py
ffxiahbot/auction/manager.py
ffxiahbot/auction/seller.py
ffxiahbot/auction/worker.py
ffxiahbot/scrubbing/__init__.py
ffxiahbot/scrubbing/enums.py
ffxiahbot/scrubbing/ffxiah.py
ffxiahbot/scrubbing/scrubber.py
ffxiahbot/tables/__init__.py
ffxiahbot/tables/auctionhouse.py
ffxiahbot/tables/base.py
ffxiahbot-7.0.1.dist-info/METADATA
ffxiahbot-7.0.1.dist-info/WHEEL
ffxiahbot-7.0.1.dist-info/entry_points.txt
ffxiahbot-7.0.1.dist-info/licenses/LICENSE
ffxiahbot-7.0.1.dist-info/RECORD
