Metadata-Version: 2.4
Name: ffxiahbot
Version: 7.0.1
Summary: A command line tool for interacting with a FFXI server.
Project-URL: Documentation, https://AdamGagorik.github.io/ffxiahbot
Project-URL: Repository, https://github.com/AdamGagorik/ffxiahbot
Author-email: Adam Gagorik <adam.gagorik@gmail.com>
License: MIT License
License-File: LICENSE
Requires-Python: >=3.13
Requires-Dist: aiohttp>=3.13.2
Requires-Dist: apscheduler>=3.10.4
Requires-Dist: beautifulsoup4>=4.12.3
Requires-Dist: click>=8.1.7
Requires-Dist: pandas>=2.2.2
Requires-Dist: pydantic>=2.8.2
Requires-Dist: pymysql>=1.1.1
Requires-Dist: pyyaml>=6.0.2
Requires-Dist: rich>=13.8.0
Requires-Dist: sqlalchemy>=2.0.32
Requires-Dist: typer>=0.12.5
